SmarTool/__init__.py
SmarTool/dtutil.py
SmarTool/flatter.py
SmarTool/retry.py
SmarTool/timeout.py
SmarTool-1.0.9.dist-info/LICENSE
SmarTool-1.0.9.dist-info/METADATA
SmarTool-1.0.9.dist-info/WHEEL
SmarTool-1.0.9.dist-info/top_level.txt
SmarTool-1.0.9.dist-info/zip-safe
SmarTool-1.0.9.dist-info/RECORD
